ini_crud/__init__.py
ini_crud/__version__.py
ini_crud/cli.py
ini_crud/core.py
ini_crud/errors.py
ini_crud/logs.py
ini_crud/utils.py
ini_crud-1.0.0.dist-info/LICENSE
ini_crud-1.0.0.dist-info/METADATA
ini_crud-1.0.0.dist-info/WHEEL
ini_crud-1.0.0.dist-info/entry_points.txt
ini_crud-1.0.0.dist-info/top_level.txt
ini_crud-1.0.0.dist-info/RECORD
