Metadata-Version: 2.1
Name: ini-crud
Version: 1.0.0
Summary: a simple tool for ini file crud
Home-page: https://github.com/hujianli94/ini_crud.ini
Author: hujianli
Author-email: 1879324764@qq.com
License: MIT
Platform: UNKNOWN
Classifier: License :: OSI Approved :: MIT License
Classifier: Programming Language :: Python
Classifier: Operating System :: OS Independent
Classifier: Programming Language :: Python :: 3.8
Classifier: Programming Language :: Python :: 3.9
Classifier: Programming Language :: Python :: 3.10
Classifier: Programming Language :: Python :: Implementation :: CPython
Classifier: Programming Language :: Python :: Implementation :: PyPy
Requires-Python: >=3.8.0
